image_mining
