Metadata-Version: 1.0
Name: image-mining
Version: 0.1.3
Summary: Extract useful information from scanned images using OpenCV
Home-page: https://github.com/acdha/image-mining/
Author: Chris Adams
Author-email: chris@improbable.org
License: LICENSE.txt
Platform: UNKNOWN
